AUTHORS.rst
CONTRIBUTING.rst
HISTORY.rst
LICENSE
MANIFEST.in
README.rst
setup.cfg
setup.py
docs/Makefile
docs/api_reference.rst
docs/authors.rst
docs/conf.py
docs/contributing.rst
docs/history.rst
docs/index.rst
docs/installation.rst
docs/make.bat
docs/readme.rst
docs/usage.rst
multihash/__init__.py
multihash/constants.py
multihash/multihash.py
planetmint_multiformat_multihash.egg-info/PKG-INFO
planetmint_multiformat_multihash.egg-info/SOURCES.txt
planetmint_multiformat_multihash.egg-info/dependency_links.txt
planetmint_multiformat_multihash.egg-info/not-zip-safe
planetmint_multiformat_multihash.egg-info/requires.txt
planetmint_multiformat_multihash.egg-info/top_level.txt
tests/test_multihash.py