Metadata-Version: 2.1
Name: planetmint-multiformat-multihash
Version: 2.1.1
Summary: Multihash implementation in Python
Home-page: https://github.com/planetmint/py-multihash
Author: Dhruv Baldawa
Author-email: dhruv@dhruvb.com
License: MIT license
Keywords: multihash
Classifier: Development Status :: 2 - Pre-Alpha
Classifier: Intended Audience :: Developers
Classifier: License :: OSI Approved :: MIT License
Classifier: Natural Language :: English
Classifier: Programming Language :: Python :: 3
Classifier: Programming Language :: Python :: 3.6
Classifier: Programming Language :: Python :: 3.7
Classifier: Programming Language :: Python :: 3.8
Classifier: Programming Language :: Python :: 3.9
Requires-Python: >=3.6
License-File: LICENSE
License-File: AUTHORS.rst
